qyout/__init__.py
qyout/config.py
qyout/main.py
qyout/main_window.py
qyout-0.5.dist-info/METADATA
qyout-0.5.dist-info/WHEEL
qyout-0.5.dist-info/entry_points.txt
qyout-0.5.dist-info/top_level.txt
qyout-0.5.dist-info/RECORD
