Metadata-Version: 2.1
Name: qyout
Version: 0.5
Summary: Qt YOUTube downloader GUI
Author: Guitouu31
License: MIT License
Project-URL: Homepage, https://github.com/guitouu31/qyout.git
Keywords: yt-dlp,youtube,qt,gui,download
Classifier: Programming Language :: Python :: 3
Classifier: License :: OSI Approved :: MIT License
Classifier: Operating System :: POSIX :: Linux
Classifier: Environment :: X11 Applications :: Qt
Classifier: Topic :: Utilities
Requires-Python: >=3.9
Requires-Dist: pyqt6
Requires-Dist: yt-dlp
